bluesnap/__init__.py
bluesnap/client.py
bluesnap/exceptions.py
bluesnap/models.py
bluesnap/resources.py
bluesnap/version.py
bluesnap/constants/__init__.py
bluesnap/constants/brands.py
tests/__init__.py
tests/helper.py
tests/mocked_api.py
tests/test_client.py
tests/test_models.py
tests/test_resources.py
bluesnap-1.2025.4.6.dist-info/LICENSE
bluesnap-1.2025.4.6.dist-info/METADATA
bluesnap-1.2025.4.6.dist-info/WHEEL
bluesnap-1.2025.4.6.dist-info/top_level.txt
bluesnap-1.2025.4.6.dist-info/RECORD
