Metadata-Version: 2.1
Name: bluesnap
Version: 1.2025.4.6
Summary: A Python 3 module to interact with the Bluesnap API.
Home-page: https://github.com/mayple/bluesnap
Author: Alon Diamant
Author-email: Alon Diamant <alon@mayple.com>
License: MIT
Project-URL: Homepage, https://github.com/mayple/bluesnap
Project-URL: Issues, https://github.com/mayple/bluesnap/issues
Classifier: Programming Language :: Python :: 3
Classifier: Operating System :: OS Independent
Requires-Python: >=3.4
License-File: LICENSE
